{
"m0001":"文件",
"m0002":"编辑",
"m0003":"视图",
"m0004":"选择",
"m0005":"查找",
"m0006":"语言",
"m0007":"帮助",
"m1008" : "代码美化",

"m0008":"在当前缓冲区中查找",
"m0009":"查找选项:",
"m000A":"查找",
"m000B":"查找全部",
"m000C":"替换",
"m000D":"全部替换",
"m000E":"清除",
"m000F":"隐藏",

"m000G":"帮助",
"m000H":"文件列表",
"m000I":"输出",
"m000J":"设置",

"d0001":"确定",
"d0002":"取消",
"d0003":"是",
"d0004":"否",
"d0005":"关闭",

"d0101":"选择一个项目:",
"d0102":"远程文件内容",
"d0103":"手动合并",
"d0104":"使用本地",
"d0105":"使用远程",
"d0106":"更改的补丁",
"d0107":"加载",
"d0108":"拖放文件到这里......",
"d0109":"或单击此处",
"d010A":"浏览...",
"d010B":"上传到:",
"d010C":"选择一个 文件(TAB) 用于与当前文件比较",
"d010D": "点击要比较的文件的 TAB",

"m0101":"新文件..",
"m0102":"创建目录..",
"m0103":"删除文件",
"m0104":"删除目录",
"m0105":"上传..",
"m0106":"下载",
"m0107":"解压缩文件",
"m0108":"压缩 文件/目录",
"m0109":"复制到..",
"m010A":"移动到..",
"m010B":"保存 &amp; 关闭项目",

"m0201":"打开..",
"m0202":"保存",
"m0203":"另存为..",
"m0204":"全部保存",
"m0205":"关闭",
"m0206":"全部关闭",
"m0207":"设置",
"m0208":"配置文件",
"m0209":"退出",
"m0210":"放弃",
"m0211":"什么都不做",

"m0301":"撤消",
"m0302":"重做",
"m0303":"剪切",
"m0304":"复制",
"m0305":"粘贴",
"m0306":"切换注释",
"m0307":"转换为大写",
"m0308":"转换为小写",
"m0309":"Unix 行模式 (LF)",
"m030A":"Windows 行模式 (CR + LF)",
"m030B":"切换书签",
"m030C":"跳转到下一个书签",
"m030D":"跳转到上一个书签",
"m030E":"转到行",
"m030F":"比较缓冲区内容",

"m0401":"切换全屏",
"m0402":"切换树视图",
"m0403":"切换输出视图",
"m0404":"切换软换行",
"m0405":"增加字体大小",
"m0406":"减小字体大小",
"m0407":"重置字体大小",

"m0501":"上面一行添加选择",
"m0502":"下面一行添加选择",
"m0503":"选择对齐到行",
"m0504":"单项选择",
"m0505":"选择至顶部",
"m0506":"选择至底部",
"m0507":"选择行",
"m0508":"选择词",
"m0509":"选择开始的词",
"m0511":"选择开始的线",
"m0512":"选择词的结尾",
"m0513":"选择到行尾",
"m0514":"选择全部",

"m0601":"在缓冲区中查找",
"m0602":"查找下一个",
"m0603":"查找上一个",
"m0604":"在项目中查找",

"m0701":"Wiki",
"m0702":"开发文档",
"m0703":"关于",

"s0001":"找不到 'init_service' 参数",
"s0002":"完成",
"s0003":"加载默认 project(fs) 失败:",
"s0004":"服务 service_url 失败",
"s0005":"[未命名的项目]",
"s0006":"超时查找节点。",
"s0007":"输入新文件名称",
"s0008":"父目录",
"s0011":"有此目录中的文件打开",
"s0012":"删除目录",
"s0014":"删除目录失败",
"s0016":"不能删除打开文件",
"s0009":"创建文件失败",
"s0017":"删除文件",
"s0019":"删除文件失败",
"s0021":"仅可在目录中",
"s0015":"请选择一个文件",
"s0013":"请输入 <b>\"yes\"</b> 确认。或输入 <b>\"all\"</b> 要删除目录,其内容以递归方式</b>",
"s0018":"请输入 <b>\"yes\"</b> 确认。",
"s0020":"请选择一个父目录",
"s0010":"请选择一个目录",
"s0022":"输入新目录名称",
"s0023":"父目录",
"s0024":"创建目录失败",
"s0025":"只下载文件",
"s0026":"打开目录失败",
"s0027":"服务 'read' 失败",
"s0028":"现在正在加载,请稍候...",
"s0029":"打开文件失败",
"s0030":"读取的服务必须设置 \"uptime\"头",
"s0031":"文件改变了",
"s0032":"保存或放弃对当前文件的更改吗？",
"s0033":"保存文件失败",
"s0034":"服务 dir 失败",
"s0035":"找不到文件",
"s0036":"不是文件",
"s0037":"参数错误",
"s0038":"无法读取文件",
"s0039":"创建差异失败",
"s0040":"服务 'write' 失败",
"s0041":"空文件不能保存",
"s0042":"不能将文件移动到其他项目",
"s0043":"移动完成, 需要刷新",
"s0044":"移动",
"s0045":"复制",
"s0046":"复制完整, 需要刷新",
"s0047":"文件 / 目录",
"s0048":"点击文件数选择文件或目录",
"s0049":"上传..",
"s0050":"不能让创建差异",
"s0051":"远程文件",
"s0052":"本地文件",
"s0053":"URL 无效",
"s0054":"不能将文件保存, 保存函数错误",
"s0055":"事件回调",
"s0056":"事件已经销毁",
"s0057":"菜单单击事件:",
"s0058":"热键错误",
"s0059":"未知键:",
"s0060":"关闭所有文件失败:",
"s0061":"搜索结果",
"s0062":"到",

"x0001":"没有打开任何文件",
"x0002":"不能退出到任何地方",
"x0003":"到达文件末尾",
"x0004":"到达文件开始",
"x0005":"转到行",
"x0006":"当前行",
"x0007":"列",
"x0008":"请输入的行号",
"x0009":"字体大小",
"x0010":"找不到任何结果",
"x0011":"已经替换",
"x0012":"请选择一个项目",
"x0013":"在项目中的查找",
"x0014":"输入字符串多于 3 个字符",
"x0015":"查找文本必须超过 3 个字符",
"x0016":"服务 'find_in_file' 失败",
"x0017":"更改语言",
"x0018":"更改语言失败"
}
